[{"url":"http://www.dataisnature.com","n_items":"10","lang":"en-US","categories":["Arte"],"title":"Dataisnature","description":"Interrelationships between natural processes, computational systems and procedural-based art practices"},{"n_items":"20","categories":["Actualidad","StartUps"],"lang":"en","url":"http://techcrunch.com","description":"Startup and Technology News","title":"TechCrunch"},{"description":"Making music with technology","title":"Create Digital Music","n_items":"10","categories":["Sonido","Actualidad"],"lang":"en-US","url":"http://createdigitalmusic.com"},{"url":"http://salonkritik.net/","categories":["Arte","Crítica"],"n_items":"15","lang":"es","title":"| :: salonKritik :: |","description":"arte | cultura | crítica"}]